lgbm_to_code/__init__.py
lgbm_to_code/lgbm_to_code.py
lgbm_to_code-0.2.1.dist-info/LICENSE
lgbm_to_code-0.2.1.dist-info/METADATA
lgbm_to_code-0.2.1.dist-info/WHEEL
lgbm_to_code-0.2.1.dist-info/top_level.txt
lgbm_to_code-0.2.1.dist-info/RECORD
