Metadata-Version: 2.1
Name: lgbm-to-code
Version: 0.2.1
Summary: Convert a trained LGBM instance into conditionals that return the same output as a predict function. Supports javascript, python and C++.
Home-page: https://github.com/danielgaskins/lgbm-to-code
Author: Daniel Gaskins
Author-email: danielgaskins99@gmail.com
Classifier: Programming Language :: Python :: 3
Classifier: License :: OSI Approved :: MIT License
Classifier: Operating System :: OS Independent
Requires-Python: >=3.6
License-File: LICENSE
Requires-Dist: lightgbm
